tei2neo/__init__.py
tei2neo/main.py
tei2neo/parse.py
tei2neo/toc.py
tei2neo-0.6.1.dist-info/METADATA
tei2neo-0.6.1.dist-info/WHEEL
tei2neo-0.6.1.dist-info/entry_points.txt
tei2neo-0.6.1.dist-info/top_level.txt
tei2neo-0.6.1.dist-info/RECORD
