Metadata-Version: 2.1
Name: tei2neo
Version: 0.6.1
Summary: TEI (Text Encoding Initiative) parser to extract information and store it in Neo4j database
Home-page: https://sissource.ethz.ch/sis/semper-tei
Author: Swen Vermeul • ID SIS • ETH Zürich
Author-email: swen@ethz.ch
License: BSD
Classifier: Programming Language :: Python :: 3
Classifier: License :: OSI Approved :: Apache Software License
Classifier: Operating System :: OS Independent
Requires-Python: >=3.5
Requires-Dist: pytest
Requires-Dist: py2neo>=2021.0.1
Requires-Dist: bs4
Requires-Dist: lxml
Requires-Dist: spacy
Requires-Dist: requests
Requires-Dist: gitpython
Requires-Dist: openpyxl
